[
    {
        "id": 1,
        "name": "Cafe Laurel",
        "type": "cafeteria",
        "adress": "Av. del Roble 660-Local A2-111, Valle del Campestre, 66265 San Pedro Garza Garcia, N.L.",
        "lat": "25.648984986698732",
        "long": "-100.35522425264874",
        "description": "Restaurante casual de Grupo Pangea que ofrece comfort food para desayunar o comer. Con ambiente relajado y cocina abierta, destaca por sus chilaquiles, toasts, pastas, panaderia artesanal y cocteleria ligera."
    },
    {
        "id": 2,
        "name": "Cafeteria Libreria Gandhi",
        "type": "cafeteria",
        "adress": "Miguel Hidalgo y Costilla 1171, Mirador, 64000 Nuevo León, N.L.",
        "lat": "25.670337001671307",
        "long": "-100.33175918691522",
        "description": "Espacio que combina una librería con cafetería de especialidad, ideal para leer, estudiar o trabajar. Ofrece café, repostería, chilaquiles y un ambiente tranquilo rodeado de libros y buena música."
    },
    {
        "id": 3,
        "name": "Café Cacao",
        "type": "cafeteria",
        "adress": "Av. Del Estado 203 A, Tecnológico, 64700 Monterrey, N.L.",
        "lat": "25.650452316765524",
        "long": "-100.29355876432308",
        "description": "Cafetería artesanal con ambiente acogedor y moderno, perfecta para reuniones o trabajo. Sirve café de especialidad, tés, y panadería fresca con opciones dulces y saladas como focaccias y panqués."
    },
    {
        "id": 4,
        "name": "Café Limón",
        "type": "cafeteria",
        "adress": "Av. Junco de la Vega 308, Nueva España, 64840 Monterrey, N.L.",
        "lat": "25.647734958464582",
        "long": "-100.28506656770391",
        "description": "Cafetería con un ambiente fresco y moderno, ideal para desayunos y tardes tranquilas. Ofrece café de especialidad, repostería artesanal y opciones saludables como bowls y tostadas, en un entorno luminoso y acogedor."
    },
    {
        "id": 5,
        "name": "Alchemy Coffee",
        "type": "cafeteria",
        "adress": "Bruselas 902, Mirador, 64070 Monterrey, N.L.",
        "lat": "25.669204417520078",
        "long": "-100.33326077342582",
        "description": "Espacio contemporáneo dedicado al café de especialidad, reconocido por su atención al detalle en métodos de extracción. Su ambiente minimalista y tranquilo lo convierte en un punto ideal para trabajar, conversar o disfrutar de postres caseros."
    },
    {
        "id": 6,
        "name": "Lázaro & Diego",
        "type": "restaurante",
        "adress": "Eje Metropolitano 10 2400, Zona Loma Larga Oriente, 66278 Monterrey, N.L.",
        "lat": "25.650524126964658",
        "long": "-100.33367626772403",
        "description": "Restaurante contemporáneo de cocina mexicana con un toque moderno, donde los ingredientes locales se combinan con técnicas innovadoras. Su ambiente elegante y cálido lo hace ideal para cenas o reuniones especiales."
    },
    {
        "id": 7,
        "name": "Jabalina",
        "type": "restaurante",
        "adress": "Padre Mier 859, Barrio Antiguo, Centro, 64000 Monterrey, N.L.",
        "lat": "25.667360066142738",
        "long": "-100.30810691324342",
        "description": "Ubicado en el corazón del Barrio Antiguo, ofrece una propuesta gastronómica moderna con influencia mediterránea. Su ambiente íntimo y su carta de vinos cuidadosamente seleccionada crean una experiencia relajada y sofisticada."
    },
    {
        "id": 8,
        "name": "Mochomos",
        "type": "restaurante",
        "adress": "Av Lázaro Cárdenas 2400, Zona Loma Larga Oriente, 66260 Monterrey, N.L.",
        "lat": "25.65050624588425",
        "long": "-100.3333265470413",
        "description": "Restaurante sonorense de alta cocina reconocido por sus cortes de carne, mariscos y mixología. Ofrece un ambiente elegante y vibrante, ideal para comidas de negocio o cenas especiales en Monterrey."
    },
    {
        "id": 9,
        "name": "Los Hidalgos",
        "type": "restaurante",
        "adress": "Av Lázaro Cárdenas 2660, Zona Valle Oriente, 66266 San Pedro Garza García, N.L.",
        "lat": "25.64729864327241",
        "long": "-100.32718832777034",
        "description": "Clásico restaurante regiomontano especializado en cortes y comida mexicana tradicional. Su servicio atento y su ambiente familiar lo han convertido en un referente para disfrutar de una buena carne asada."
    },
    {
        "id": 10,
        "name": "Fonda El Limoncito",
        "type": "restaurante",
        "adress": "Guillermo Prieto 938, entre Mina y Diego de Montemayor, Barrio Antiguo, Centro, 64000 Monterrey, N.L.",
        "lat": "25.663984026823993",
        "long": "-100.30759487620364",
        "description": "Restaurante de cocina mexicana tradicional con ambiente rústico y hogareño. Ofrece platillos caseros, desayunos completos y aguas frescas, evocando el sabor de las fondas típicas de México."
    },
    {
        "id": 11,
        "name": "Paseo Santa Lucía",
        "type": "emblematico",
        "adress": "Centro, 64000 Monterrey, N.L.",
        "lat": "25.67199501251882",
        "long": "-100.29784878731996",
        "description": "Canal artificial y paseo turístico icónico de Monterrey que conecta el Parque Fundidora con el centro. Ofrece recorridos en lancha, áreas para caminar y vistas urbanas únicas."
    },
    {
        "id": 12,
        "name": "Barrio Antiguo",
        "type": "emblematico",
        "adress": "Centro, 64000 Monterrey, N.L.",
        "lat": "25.666948562632818",
        "long": "-100.306173009285",
        "description": "Zona histórica y cultural del centro de Monterrey, famosa por su arquitectura colonial, galerías, bares y restaurantes. Es un punto clave para el arte, la música y la vida nocturna."
    },
    {
        "id": 13,
        "name": "Museo de Arte Contemporáneo",
        "type": "emblematico",
        "adress": "Juan Zuazua, Padre Raymundo Jardón y, Centro, 64000 Monterrey, N.L.",
        "lat": "25.664729733577616",
        "long": "-100.30979191188067",
        "description": "Espacio dedicado al arte moderno y contemporáneo, reconocido por su arquitectura icónica. Exhibe obras nacionales e internacionales y cuenta con un ambiente cultural vibrante."
    },
    {
        "id": 14,
        "name": "Museo de Historia Mexicana",
        "type": "emblematico",
        "adress": "Dr. José Ma. Coss 445, Centro, 64000 Monterrey, N.L.",
        "lat": "25.671674225087937",
        "long": "-100.30645552888112",
        "description": "Museo que ofrece una visión completa de la historia de México desde las civilizaciones prehispánicas hasta la actualidad. Ideal para conocer la identidad cultural del país."
    },
    {
        "id": 15,
        "name": "Parque Fundidora",
        "type": "emblematico",
        "adress": "Adolfo Prieto S/N, Obrera, 64010 Monterrey, N.L.",
        "lat": "25.67858972056601",
        "long": "-100.28420744667727",
        "description": "Antiguo complejo industrial transformado en un parque urbano emblemático. Alberga museos, foros, áreas verdes y eventos culturales, siendo uno de los principales atractivos de Monterrey."
    },
    {
        "id": 16,
        "name": "Parque Cinema",
        "type": "evento",
        "adress": "Parque Bosques, Bosque del Olivo, Avenida Bosques del Valle, Av Alfonso Reyes y, San Pedro Garza García, N.L.",
        "lat": "25.645361788477604",
        "long": "-100.37671259188197",
        "description": "Evento de cine al aire libre en San Pedro, donde se proyectan películas en un entorno natural. Ofrece un ambiente familiar y relajado, con opciones de comida y actividades recreativas."
    },
    {
        "id": 17,
        "name": "Ballet de Monterrey",
        "type": "evento",
        "adress": "Dr. José Ma. Coss 732, Centro, 64000 Monterrey, N.L.",
        "lat": "25.66903889855954",
        "long": "-100.30888800186995",
        "description": "Disfruta de un ballet por la compañía insignia de Monterrey, reconocida por su calidad artística y producciones clásicas y contemporáneas, presenta espectáculos de danza profesional en los principales teatros de la ciudad."
    },
    {
        "id": 18,
        "name": "Obra de Teatro",
        "type": "evento",
        "adress": "Av. Eugenio Garza Sada 2501, Tecnológico, 64700 Monterrey, N.L.",
        "lat": "25.6506502315807",
        "long": "-100.28541554481367",
        "description": "Asiste a las diferentes funciones teatrales presentadas en espacios culturales de Monterrey, con propuestas locales y nacionales. Promueve el arte escénico y la participación del público en experiencias en vivo."
    },
    {
        "id": 19,
        "name": "Candlelight Concerts",
        "type": "evento",
        "adress": "Juan Zuazua, Padre Raymundo Jardón y, Centro, 64000 Monterrey, N.L.",
        "lat": "25.664729733577616",
        "long": "-100.30979191188067",
        "description": "Disfruta de un concierto íntimo a la luz de las velas que combina música clásica y contemporánea en locaciones emblemáticas. Ofrecen una experiencia sensorial y elegante."
    },
    {
        "id": 20,
        "name": "Música Mariachi en Vivo",
        "type": "evento",
        "adress": "Priciliano Elizondo, Av. Francisco I. Madero, 64000 Monterrey, N.L.",
        "lat": "25.68277779881671",
        "long": "-100.28324291925867",
        "description": "Goza de este evento cultural que celebra la música tradicional mexicana con mariachis en directo. Ideal para disfrutar de canciones emblemáticas y un ambiente festivo y familiar."
    },
    {
        "id": 21,
        "name": "Limpieza de Parques",
        "type": "voluntariado",
        "adress": "Av. Fuentes del Valle, Fuentes del Valle, 66220 San Pedro Garza García, N.L.",
        "lat": "25.665067418079577",
        "long": "-100.36144939148897",
        "description": "Actividad comunitaria enfocada en conservar áreas verdes y fomentar la conciencia ambiental. Ideal para participar en familia o con amigos contribuyendo al bienestar urbano."
    },
    {
        "id": 22,
        "name": "Comedores conscientes",
        "type": "voluntariado",
        "adress": "Calle Castelar 1490, Pío X, 64710 Monterrey, N.L.",
        "lat": "25.660234600748733",
        "long": "-100.32983146566436",
        "description": "Iniciativa social que brinda alimentos nutritivos a comunidades vulnerables. Promueve el consumo responsable y la solidaridad a través del voluntariado activo."
    },
    {
        "id": 23,
        "name": "Paseo de perros",
        "type": "voluntariado",
        "adress": "José Antonio Rodríguez 1702, La Esperanza, 64237 Monterrey, N.L.",
        "lat": "25.743971891602403",
        "long": "-100.34795503210403",
        "description": "Actividad recreativa y de voluntariado para pasear perros rescatados, fomentando su socialización y bienestar. Ideal para amantes de los animales y la adopción responsable."
    },
    {
        "id": 24,
        "name": "Apadrina a un niño",
        "type": "voluntariado",
        "adress": "Valparaíso 801, Sin Nombre de Col 33, 67140 Guadalupe, N.L.",
        "lat": "25.669534313541163",
        "long": "-100.25241658365948",
        "description": "Programa solidario que conecta voluntarios con niños en situación vulnerable, ofreciendo apoyo educativo y emocional. Busca generar impacto positivo en su desarrollo."
    },
    {
        "id": 25,
        "name": "Apoya a anciano",
        "type": "voluntariado",
        "adress": "C. San Luis 302, La Pastora, 67140 Guadalupe, N.L.",
        "lat": "25.66616822743072",
        "long": "-100.26151948670619",
        "description": "Actividad de acompañamiento a adultos mayores mediante visitas, donaciones y apoyo emocional. Promueve la empatía, la escucha y el bienestar en la tercera edad."
    }
]
